Metadata-Version: 2.1
Name: richlog
Version: 0.3.2
Summary: log filename timestamp linenumber
Home-page: https://github.com/metacryptosec/log.git
Author: www.metacryptosec.com
Author-email: blockchaindeveloper123@gmail.com
License: MIT Licence
Keywords: pip,log
Platform: any
